ipyquizjb/__init__.py
ipyquizjb/faceit.py
ipyquizjb/latex.py
ipyquizjb/question_widgets.py
ipyquizjb/questions.py
ipyquizjb/types.py
ipyquizjb/utils.py
ipyquizjb-0.3.13.dist-info/METADATA
ipyquizjb-0.3.13.dist-info/WHEEL
ipyquizjb-0.3.13.dist-info/licenses/LICENSE
ipyquizjb-0.3.13.dist-info/RECORD
